hra_etl/BaseTable.py
hra_etl/__init__.py
hra_etl/labio/__init__.py
hra_etl/labio/argParseWrapper.py
hra_etl/labio/configWrapper.py
hra_etl/labio/dbWrapper.py
hra_etl/labio/logWrapper.py
hra_etl/labio/utils.py
hra_etl/labio/validators.py
hra_etl-0.0.4.dist-info/METADATA
hra_etl-0.0.4.dist-info/WHEEL
hra_etl-0.0.4.dist-info/top_level.txt
hra_etl-0.0.4.dist-info/RECORD
