Metadata-Version: 2.1
Name: hra-etl
Version: 0.0.4
Summary: A small example package
Home-page: https://gitlab.dell.com/corporate/hr-data-lake/ETL/etl-architecture
Author: Gyanendra Kumar Patro
Author-email: gyanendrapatro02@gmail.com
License: UNKNOWN
Keywords: ETL,PYTHONETL,PYTHON
Platform: UNKNOWN
Classifier: Programming Language :: Python :: 3
Classifier: Programming Language :: Python :: 3.4
Classifier: Programming Language :: Python :: 3.5
Classifier: Programming Language :: Python :: 3.6
Classifier: License :: OSI Approved :: MIT License
Classifier: Operating System :: OS Independent
Requires-Dist: pyodbc
Requires-Dist: pandas
Requires-Dist: gnupg
Requires-Dist: chardet
Requires-Dist: datetime
Requires-Dist: configparser
